setup.cfg
setup.py
RhubarbTart.egg-info/PKG-INFO
RhubarbTart.egg-info/SOURCES.txt
RhubarbTart.egg-info/entry_points.txt
RhubarbTart.egg-info/not-zip-safe
RhubarbTart.egg-info/paster_plugins.txt
RhubarbTart.egg-info/requires.txt
RhubarbTart.egg-info/top_level.txt
docs/community.txt
docs/index.txt
docs/todo.txt
docs/user-tutorial.txt
rhubarbtart/__init__.py
rhubarbtart/httpobjects.py
rhubarbtart/tart_template.py
rhubarbtart/threadobject.py
rhubarbtart/paste_templates/rhubarbtart/setup.py_tmpl
rhubarbtart/paste_templates/rhubarbtart/+package+/__init__.py_tmpl
rhubarbtart/paste_templates/rhubarbtart/+package+/webroot.py_tmpl
rhubarbtart/paste_templates/rhubarbtart/+package+/wsgiapp.py_tmpl
rhubarbtart/paste_templates/rhubarbtart/docs/devel_config.ini_tmpl
rhubarbtart/paste_templates/rhubarbtart/tests/conftest.py_tmpl
rhubarbtart/paste_templates/rhubarbtart/tests/fixture.py
rhubarbtart/paste_templates/rhubarbtart/tests/test_app.py_tmpl
tests/conftest.py
tests/test_request.py
tests/test_response.py
tests/test_tart.py
