Metadata-Version: 1.0
Name: RhubarbTart
Version: 0.5
Summary: A light object publishing web framework built on WSGI and Paste
Home-page: http://rhubarbtart.org
Author: Julian Krause
Author-email: thecrypto@thecrypto.org
License: MIT
Keywords: wsgi web freamework
Platform: UNKNOWN
Classifier: Development Status :: 3 - Alpha
Classifier: Intended Audience :: Developers
Classifier: License :: OSI Approved :: MIT License
Classifier: Programming Language :: Python
Classifier: Topic :: Internet :: WWW/HTTP
Classifier: Topic :: Internet :: WWW/HTTP :: Dynamic Content
Classifier: Topic :: Software Development :: Libraries :: Python Modules
